split_qr_exam/__init__.py
split_qr_exam/main.py
split_qr_exam-0.1.3.dist-info/LICENSE
split_qr_exam-0.1.3.dist-info/METADATA
split_qr_exam-0.1.3.dist-info/WHEEL
split_qr_exam-0.1.3.dist-info/entry_points.txt
split_qr_exam-0.1.3.dist-info/top_level.txt
split_qr_exam-0.1.3.dist-info/RECORD
