Metadata-Version: 2.1
Name: split-qr-exam
Version: 0.1.3
Summary: Splits a pdf consisting of multiple exams identified by a QR code on the cover page
Home-page: https://github.com/christofsteel/split_qr_exam.git
Author: Christoph Stahl
Author-email: christoph.stahl@tu-dortmund.de
License: UNKNOWN
Platform: UNKNOWN
Classifier: Programming Language :: Python :: 3
Classifier: Operating System :: OS Independent
Classifier: Development Status :: 4 - Beta
Classifier: License :: OSI Approved :: GNU General Public License v3 or later (GPLv3+)
Classifier: Environment :: Console
Classifier: Intended Audience :: Education
Classifier: Topic :: Education
Classifier: Topic :: Multimedia :: Graphics
Classifier: Topic :: Utilities
Requires-Python: >=3.6
Requires-Dist: numpy
Requires-Dist: pymupdf
Requires-Dist: opencv-python-headless
